{
    "@context": {
        "kb": "http://example.org/kb/",
        "uco-observable": "https://ontology.unifiedcyberontology.org/uco/observable#"
    },
    "@graph": [
        {
            "@id": "kb:softwarefacet1",
            "@type": "uco-observable:SoftwareFacet",
            "uco-observable:cpeid": null,
            "uco-observable:language": null,
            "uco-observable:manufacturer": null,
            "uco-observable:swid": null,
            "uco-observable:version": null
        }
    ],
    "@version": {
        "case_util": "0.6.0",
        "ontology_version": "0.7.0"
    }
}
