{
  "@context": {
    "kb": "http://example.org/kb/",
    "uco-observable:": "https://ontology.unifiedcyberontology.org/uco/observable#"
  },
  "@graph": [
    {
      "@id": "kb:simcardfacet1",
      "@type": "uco-observable:SIMCardFacet",
      "uco-observable:carrier": null,
      "uco-observable:storageCapacityInBytes": null,
      "uco-observable:ICCID": null,
      "uco-observable:IMSI": null,
      "uco-observable:PIN": null,
      "uco-observable:PUK": null,
      "uco-observable:SIMForm": null,
      "uco-observable:SIMType": null
    }
  ]
}