{
    "@context": {
        "kb": "http://example.org/kb/",
        "uco-observable": "https://ontology.unifiedcyberontology.org/uco/observable/",
        "xsd": "http://www.w3.org/2001/XMLSchema#"
    },
    "@graph": [
        {
            "@id": "kb:AutonomousSystemFacet-1",
            "@type": "uco-observable:AutonomousSystemFacet",
            "uco-observable:asHandle": null,
            "uco-observable:number": null,
            "uco-observable:regionalInternetRegistry": null
        }
    ]
}
